pentestkit/__init__.py
pentestkit/cli.py
pentestkit/utils.py
pentestkit/dataclasses/__init__.py
pentestkit/dataclasses/body.py
pentestkit/dataclasses/endpoint.py
pentestkit/dataclasses/parameter.py
pentestkit/fuzzer/__init__.py
pentestkit/parser/__init__.py
pentestkit/parser/base_parser.py
pentestkit/parser/openapi_parser.py
pentestkit-0.1.0.dist-info/licenses/LICENSE
tests/__init__.py
tests/test_pentestkit_init.py
tests/test_data/__init__.py
tests/test_data/test_parser_constants.py
tests/test_dataclasses/__init__.py
tests/test_dataclasses/test_parameter.py
tests/test_parser/__init__.py
tests/test_parser/test_base_parser.py
tests/test_parser/test_openapi_parser.py
pentestkit-0.1.0.dist-info/METADATA
pentestkit-0.1.0.dist-info/WHEEL
pentestkit-0.1.0.dist-info/entry_points.txt
pentestkit-0.1.0.dist-info/top_level.txt
pentestkit-0.1.0.dist-info/RECORD
