Metadata-Version: 2.4
Name: pentestkit
Version: 0.1.0
Summary: A Python library for API penetration testing using Swagger files.
Home-page: https://github.com/rahulkaushal04/pentestkit
Author: Rahul Kaushal
License: Apache-2.0
Project-URL: Source Code, https://github.com/rahulkaushal04/pentestkit
Project-URL: Issue Tracker, https://github.com/rahulkaushal04/pentestkit/issues
Keywords: API security,penetration testing,pentest,swagger,security testing
Classifier: Development Status :: 4 - Beta
Classifier: Intended Audience :: Developers
Classifier: Intended Audience :: Information Technology
Classifier: Intended Audience :: System Administrators
Classifier: Topic :: Security
Classifier: License :: OSI Approved :: Apache Software License
Classifier: Programming Language :: Python :: 3
Classifier: Programming Language :: Python :: 3.8
Classifier: Programming Language :: Python :: 3.9
Classifier: Programming Language :: Python :: 3.10
Classifier: Operating System :: OS Independent
Requires-Python: >=3.8
License-File: LICENSE
Requires-Dist: requests==2.32.3
Requires-Dist: urllib3>=2.2.3
Requires-Dist: rstr==3.2.2
Provides-Extra: dev
Requires-Dist: pytest; extra == "dev"
Requires-Dist: pytest-cov; extra == "dev"
Requires-Dist: flake8; extra == "dev"
Dynamic: author
Dynamic: classifier
Dynamic: description
Dynamic: description-content-type
Dynamic: home-page
Dynamic: keywords
Dynamic: license
Dynamic: license-file
Dynamic: project-url
Dynamic: provides-extra
Dynamic: requires-dist
Dynamic: requires-python
Dynamic: summary
